{
  "external_id": "ocds-5wno2w-SIE-04D02MBS001-2015-15025",
  "data_origin": "sercop_ocds",
  "is_demo": false,
  "title": "ADQUISICIÓN DE DISPOSITIVOS MÉDICOS PARA LOS DIFERENTES SERVICIOS DE LA DIRECCIÓN DISTRITAL 04D02 MONTÚFAR BOLÍVAR SALUD",
  "institution": "DIRECCION DISTRITAL 04D02 MONTUFAR-BOLIVAR-SALUD",
  "supplier": "REPRESENTACIONES MOLINA HERRERA M.H. CIA. LTDA.",
  "amount": "14000.000000",
  "procedure_type": "Subasta Inversa Electrónica",
  "award_date": "2015-06-24T00:00:00-05:00",
  "source_url": "https://datosabiertos.compraspublicas.gob.ec/PLATAFORMA/api/record?ocid=ocds-5wno2w-SIE-04D02MBS001-2015-15025",
  "locality": "MONTUFAR",
  "region": "CARCHI"
}