{
  "external_id": "ocds-5wno2w-CDC-GPL-003-2015-2470",
  "data_origin": "sercop_ocds",
  "is_demo": false,
  "title": "CONTRATACIÓN DE AUDITORÍA EXTERNA DEL SISTEMA DE GESTIÓN DE SEGURIDAD Y SALUD LABORAL",
  "institution": "GOBIERNO PROVINCIAL DE LOJA",
  "supplier": "TECNICOS ESPECIALISTAS EN PREVENCION DE RIESGOS OCUPACIONALES TECNIPREVEN S.A.",
  "amount": "3520.000000",
  "procedure_type": "Contratacion directa",
  "award_date": "2015-04-30T00:00:00-05:00",
  "source_url": "https://datosabiertos.compraspublicas.gob.ec/PLATAFORMA/api/record?ocid=ocds-5wno2w-CDC-GPL-003-2015-2470",
  "locality": "LOJA",
  "region": "LOJA"
}