{
  "external_id": "ocds-5wno2w-CDC-CELECEP-2024-01098-238940",
  "data_origin": "sercop_ocds",
  "is_demo": false,
  "title": "MAT-CONSULTORÍA PARA LA CERTIFICACIÓN Y SEGUIMIENTO DEL SISTEMA DE GESTIÓN ANTISOBORNO BAJO LA NORMA ISO 37001:2016 PARA CELEC EP – MATRIZ Y LAS UNIDADES DE NEGOCIO CELEC SUR, COCA CODO SINCLAIR, HIDROAGOYÁN, ELECTROGUAYAS, TERMOPICHINCHA Y TRANSELECTRIC",
  "institution": "CORPORACION ELECTRICA DEL ECUADOR CELEC EP.",
  "supplier": "AENORECUADOR S.A.",
  "amount": "9400.000000",
  "procedure_type": "Contratacion directa",
  "award_date": "2025-02-01T06:01:52-05:00",
  "source_url": "https://datosabiertos.compraspublicas.gob.ec/PLATAFORMA/api/record?ocid=ocds-5wno2w-CDC-CELECEP-2024-01098-238940",
  "locality": "QUITO",
  "region": "PICHINCHA"
}