{
  "external_id": "ocds-5wno2w-CDC-DDSCHR-001-2016-121872",
  "data_origin": "sercop_ocds",
  "is_demo": false,
  "title": "CONSULTORÍA PARA ELABORACIÓN DE LA AUDITORÍA AMBIENTAL DE CUMPLIMIENTO DEL CENTRO DE SALUD TIPO C ESPOCH – LIZARZABURU.",
  "institution": "DIRECCION DISTRITAL 06D01-CHAMBO-RIOBAMBA-SALUD",
  "supplier": "HIPO LEON LUIS FAUSTO",
  "amount": "3070.180000",
  "procedure_type": "Contratacion directa",
  "award_date": "2016-11-07T00:00:00-05:00",
  "source_url": "https://datosabiertos.compraspublicas.gob.ec/PLATAFORMA/api/record?ocid=ocds-5wno2w-CDC-DDSCHR-001-2016-121872",
  "locality": "RIOBAMBA",
  "region": "CHIMBORAZO"
}