{
  "external_id": "ocds-5wno2w-CE-20150000343613-4081",
  "data_origin": "sercop_ocds",
  "is_demo": false,
  "title": "Orden de compra para adquirir los siguientes productos:  Lencería General  (prendas que se usa dentro de los establecimientos de salud) Lencería General  (prendas que se usa dentro de los establecimientos de salud)",
  "institution": "ILUSTRE MUNICIPIO DE SANTA ELENA",
  "supplier": "ANGEL RAMIREZ MARJORIE ELIZABETH",
  "amount": "2150.400000",
  "procedure_type": "Catálogo electrónico - Compra directa",
  "award_date": "2015-09-18T00:00:00-05:00",
  "source_url": "https://datosabiertos.compraspublicas.gob.ec/PLATAFORMA/api/record?ocid=ocds-5wno2w-CE-20150000343613-4081",
  "locality": "SANTA ELENA",
  "region": "SANTA ELENA"
}