{
  "external_id": "ocds-5wno2w-CE-20260002965185-922485",
  "data_origin": "sercop_ocds",
  "is_demo": false,
  "title": "Orden de compra para adquirir los siguientes productos:  SERVICIOS DE LIMPIEZA Y MANTENIMIENTO DE VIVIENDAS O DE EDIFICIOS COMERCIALES, ADMINISTRATIVOS E INDUSTRIALE, LIMPIEZA Y ENCERADO DE PISOS",
  "institution": "MUSEO NACIONAL DEL ECUADOR",
  "supplier": "ALTA LIMPIEZA \"ALPILIMZA CIA. LTDA.\"",
  "amount": "9012.262500",
  "procedure_type": "Catálogo electrónico - Compra directa",
  "award_date": "2026-01-27T00:00:00-05:00",
  "source_url": "https://datosabiertos.compraspublicas.gob.ec/PLATAFORMA/api/record?ocid=ocds-5wno2w-CE-20260002965185-922485",
  "locality": "QUITO",
  "region": "PICHINCHA"
}