{
  "external_id": "ocds-5wno2w-MCS-DDSS-006-2015-440761",
  "data_origin": "sercop_ocds",
  "is_demo": false,
  "title": "Contratacion del Servicio para el Mantenimiento Preventivo y Correctivo de los Vehículos Livianos y motos de la Dirección Distrital 05D05-Sigchos-Salud.",
  "institution": "DIRECCION DISTRITAL 05D05 - SIGCHOS - SALUD",
  "supplier": "Quimbita Chanatasig Fernando Gonzalo",
  "amount": "10000.000000",
  "procedure_type": "Menor Cuantía",
  "award_date": "2015-03-27T00:00:00-05:00",
  "source_url": "https://datosabiertos.compraspublicas.gob.ec/PLATAFORMA/api/record?ocid=ocds-5wno2w-MCS-DDSS-006-2015-440761",
  "locality": "SIGCHOS",
  "region": "COTOPAXI"
}