{
  "external_id": "ocds-5wno2w-RE-24D01-002-101045",
  "data_origin": "sercop_ocds",
  "is_demo": false,
  "title": "CONTRATACIÓN DE LA POLIZA DE FIDELIDAD BLANKET PARA EL PERSONAL DE LA DIRECCION DISTRITAL 24D01SANTA ELENA SALUD",
  "institution": "DIRECCION DISTRITAL 24D01- SANTA ELENA - SALUD",
  "supplier": "SEGUROS SUCRE S.A.",
  "amount": "12321.710000",
  "procedure_type": "Contratación de Seguros",
  "award_date": "2015-04-09T00:00:00-05:00",
  "source_url": "https://datosabiertos.compraspublicas.gob.ec/PLATAFORMA/api/record?ocid=ocds-5wno2w-RE-24D01-002-101045",
  "locality": "SANTA ELENA",
  "region": "SANTA ELENA"
}