{
  "external_id": "ocds-5wno2w-LICS-GADMATACAMES-2026-0001-20080",
  "data_origin": "sercop_ocds",
  "is_demo": false,
  "title": "CONTRATACIÓN DE SERVICIO DE PRODUCCION DE EVENTOS CARNAVALEROS ATACAMES 2026",
  "institution": "GOBIERNO AUTONOMO DESCENTRALIZADO MUNICIPAL DE ATACAMES",
  "supplier": "Proveedor no identificado",
  "amount": "190000.000000",
  "procedure_type": "Licitación",
  "award_date": "2026-02-21T07:19:02-05:00",
  "source_url": "https://datosabiertos.compraspublicas.gob.ec/PLATAFORMA/api/record?ocid=ocds-5wno2w-LICS-GADMATACAMES-2026-0001-20080",
  "locality": "ATACAMES",
  "region": "ESMERALDAS"
}