{
  "external_id": "ocds-5wno2w-SIE-CELCCS-92B-2023-238940",
  "data_origin": "sercop_ocds",
  "is_demo": false,
  "title": "CCS REPOTENCIACION DEL SISTEMA DE CONTROL DE ASISTENCIA DE LA UNIDAD DE NEGOCIO COCA CODO SINCLAIR",
  "institution": "CORPORACION ELECTRICA DEL ECUADOR CELEC EP.",
  "supplier": "Proveedor no identificado",
  "amount": "23608.940000",
  "procedure_type": "Subasta Inversa Electrónica",
  "award_date": "2024-02-06T07:02:43-05:00",
  "source_url": "https://datosabiertos.compraspublicas.gob.ec/PLATAFORMA/api/record?ocid=ocds-5wno2w-SIE-CELCCS-92B-2023-238940",
  "locality": "CUENCA",
  "region": "AZUAY"
}