{
  "external_id": "ocds-5wno2w-SIE-CELCCS-024-20-238940",
  "data_origin": "sercop_ocds",
  "is_demo": false,
  "title": "CCS SERVICIO DE CERTIFICACIÓN DE CALIBRACIÓN ANUAL DE VÁLVULAS DE SEGURIDAD PSV PARA LA CENTRAL COCA CODO SINCLAIR",
  "institution": "CORPORACION ELECTRICA DEL ECUADOR CELEC EP.",
  "supplier": "METROLOGIC S.A.",
  "amount": "10900.080000",
  "procedure_type": "Subasta Inversa Electrónica",
  "award_date": "2020-10-19T00:00:00-05:00",
  "source_url": "https://datosabiertos.compraspublicas.gob.ec/PLATAFORMA/api/record?ocid=ocds-5wno2w-SIE-CELCCS-024-20-238940",
  "locality": "CUENCA",
  "region": "AZUAY"
}